azure/batch/__init__.py
azure/batch/_batch_service_client.py
azure/batch/_configuration.py
azure/batch/_version.py
azure/batch/batch_auth.py
azure/batch/py.typed
azure/batch/custom/__init__.py
azure/batch/custom/custom_errors.py
azure/batch/custom/patch.py
azure/batch/models/__init__.py
azure/batch/models/_batch_service_client_enums.py
azure/batch/models/_models.py
azure/batch/models/_models_py3.py
azure/batch/models/_paged_models.py
azure/batch/operations/__init__.py
azure/batch/operations/_account_operations.py
azure/batch/operations/_application_operations.py
azure/batch/operations/_certificate_operations.py
azure/batch/operations/_compute_node_extension_operations.py
azure/batch/operations/_compute_node_operations.py
azure/batch/operations/_file_operations.py
azure/batch/operations/_job_operations.py
azure/batch/operations/_job_schedule_operations.py
azure/batch/operations/_pool_operations.py
azure/batch/operations/_task_operations.py
azure_batch-14.2.0.dist-info/LICENSE
azure_batch-14.2.0.dist-info/METADATA
azure_batch-14.2.0.dist-info/WHEEL
azure_batch-14.2.0.dist-info/top_level.txt
azure_batch-14.2.0.dist-info/RECORD
